akimous/.style.yapf
akimous/__init__.py
akimous/__main__.py
akimous/completion_utilities.py
akimous/config.py
akimous/doc_generator.py
akimous/editor.py
akimous/file_finder.py
akimous/file_tree.py
akimous/interactive_shell.py
akimous/jedi_accelerator.py
akimous/jedi_preloader.py
akimous/modeling/__init__.py
akimous/modeling/completion_engine.py
akimous/modeling/download.py
akimous/modeling/extract_features.py
akimous/modeling/feature/__init__.py
akimous/modeling/feature/completion_features.py
akimous/modeling/feature/context_features.py
akimous/modeling/feature/feature_definition.py
akimous/modeling/generate_token_statistics.py
akimous/modeling/offline_feature_extractor.py
akimous/modeling/repo_downloader.py
akimous/modeling/sample.py
akimous/modeling/select_features.py
akimous/modeling/token_map.py
akimous/modeling/train.py
akimous/modeling/utility.py
akimous/modeling/visualize.py
akimous/online_feature_extractor.py
akimous/open_folder.py
akimous/project.py
akimous/pyflakes_reporter.py
akimous/resources/__init__.py
akimous/resources/bigram.xz
akimous/resources/default_config.json
akimous/resources/default_project_state.json
akimous/resources/doc_template/__init__.py
akimous/resources/doc_template/conf.py
akimous/resources/doc_template/index.rst
akimous/resources/file_templates/dockerfile/slim.dockerfile
akimous/resources/file_templates/gitignore/python.gitignore
akimous/resources/file_templates/helloworld/flask.py
akimous/resources/file_templates/helloworld/script.py
akimous/resources/file_templates/license/2-Clause BSD.txt
akimous/resources/file_templates/license/3-Clause BSD.txt
akimous/resources/file_templates/license/Apache 2.0.txt
akimous/resources/file_templates/license/GPLv3.txt
akimous/resources/file_templates/license/MIT.txt
akimous/resources/file_templates/readme/sample.md
akimous/resources/file_templates/setup/basic.py
akimous/resources/file_templates/tox/basic.ini
akimous/resources/macro.js
akimous/resources/repo.json
akimous/resources/token.xz
akimous-0.9.0.dist-info/entry_points.txt
akimous-0.9.0.dist-info/LICENSE
akimous-0.9.0.dist-info/WHEEL
akimous-0.9.0.dist-info/METADATA
akimous-0.9.0.dist-info/RECORD
