Metadata-Version: 2.1
Name: akimous
Version: 0.9.0
Summary: An intelligent Python IDE
Home-page: https://akimous.com
License: BSD-3-Clause
Keywords: ide,editor,akimous
Author: Yu-Ann Chen
Author-email: red8012@gmail.com
Requires-Python: >=3.8,<4.0
Classifier: Development Status :: 3 - Alpha
Classifier: Environment :: Web Environment
Classifier: Intended Audience :: Developers
Classifier: License :: OSI Approved :: BSD License
Classifier: Programming Language :: Python :: 3
Classifier: Programming Language :: Python :: 3 :: Only
Classifier: Programming Language :: Python :: 3.7
Classifier: Programming Language :: Python :: 3.8
Classifier: Programming Language :: Python :: 3.9
Classifier: Topic :: Software Development
Classifier: Topic :: Text Editors :: Integrated Development Environments (IDE)
Requires-Dist: Send2Trash (>=1.5,<2.0)
Requires-Dist: appdirs (>=1.4,<2.0)
Requires-Dist: cachetools (>=4.0,<5.0)
Requires-Dist: fuzzywuzzy (>=0.18.0,<0.19.0)
Requires-Dist: gitpython (>=3.1.0,<4.0.0)
Requires-Dist: ipykernel (>=5.1,<6.0)
Requires-Dist: jedi (>=0.17.0,<0.18.0)
Requires-Dist: jupyter_client (>=6.0,<7.0)
Requires-Dist: logzero (>=1.5,<2.0)
Requires-Dist: msgpack (>=1.0,<2.0)
Requires-Dist: numpy (>=1.17,<2.0)
Requires-Dist: numpydoc (>=1.0.0,<2.0.0)
Requires-Dist: pathspec (>=0.8.0,<0.9.0)
Requires-Dist: ptyprocess (>=0.6.0,<0.7.0)
Requires-Dist: pyflakes (>=2.0,<3.0)
Requires-Dist: pylint (>=2.1,<3.0)
Requires-Dist: python-levenshtein (>=0.12.0,<0.13.0)
Requires-Dist: sphinx (>=3.0,<4.0)
Requires-Dist: toml (>=0.10.0,<0.11.0)
Requires-Dist: watchdog (>=0.10.0,<0.11.0)
Requires-Dist: websockets (>=8.0,<9.0)
Requires-Dist: wordsegment (>=1.3,<2.0)
Requires-Dist: xgboost (>=1.0,<2.0)
Requires-Dist: yapf (>=0.30.0,<0.31.0)
Project-URL: Documentation, https://akimous.com/start
Project-URL: Repository, https://github.com/akimous/akimous
